eap2api/__init__.py
eap2api-0.1.0.dist-info/METADATA
eap2api-0.1.0.dist-info/WHEEL
eap2api-0.1.0.dist-info/top_level.txt
eap2api-0.1.0.dist-info/RECORD
