Metadata-Version: 2.4
Name: eap2api
Version: 0.1.0
Summary: Library for make tkinter easier
Author-email: Wuaze <jorgehoyaprado1@gmail.com>
Requires-Python: >=3.9
